.gitignore
README.md
buildout.cfg
requirements.txt
setup.py
versions.cfg
kc_utils/__init__.py
kc_utils.egg-info/PKG-INFO
kc_utils.egg-info/SOURCES.txt
kc_utils.egg-info/dependency_links.txt
kc_utils.egg-info/requires.txt
kc_utils.egg-info/top_level.txt
kc_utils/cache/__init__.py
kc_utils/cache/redis_helper.py
kc_utils/time/__init__.py