Metadata-Version: 2.1
Name: kc-utils
Version: 0.0.1
Summary: kc_utils
Home-page: https://github.com/kcoo/kc_utils
Author: yc.fqiyou
Author-email: yc.fqiyou@gmail.com
License: UNKNOWN
Platform: UNKNOWN
Provides-Extra: cache_redis
